myfiglet/__init__.py
myfiglet-0.0.9.dist-info/METADATA
myfiglet-0.0.9.dist-info/WHEEL
myfiglet-0.0.9.dist-info/top_level.txt
myfiglet-0.0.9.dist-info/RECORD
