Metadata-Version: 2.1
Name: myfiglet
Version: 0.0.9
Summary: FIGlet Using Python
Author: Harsh Gupta
Author-email: harshnkgupta@gmail.com
